src/Memory/DepFIFO.sv
// Name: Leonard Paya, Bernardo Lin
// Date: 2026-05-25
// Saturating entry counter tracking in-flight RAW/WAR dependency slots; exposes full/empty status to the sequencer.
// Parameters:
//     - DEPTH: Max number of concurrent in-flight dependencies tracked
// Inputs:
//     - clk: System clock
//     - rst: Active-high synchronous reset
//     - push: Increment count — new dependency slot acquired
//     - pop: Decrement count — dependency resolved
// Outputs:
//     - full: Asserted when count == DEPTH; no more slots available
//     - empty: Asserted when count == 0; no pending dependencies

module DepFIFO #(
    parameter int DEPTH = 4
) (
    input  logic clk, rst,
    input  logic push, pop,
    output logic full, empty
);

    logic [$clog2(DEPTH):0] mem;

    always_ff @(posedge clk) begin
        if (rst) begin
            mem <= '0;
        end else begin
            case ({push, pop})
                2'b10:   mem <= mem + 1;
                2'b01:   mem <= mem - 1;
                default: mem <= mem;
            endcase
        end
    end

    assign full  = (mem == DEPTH);
    assign empty = (mem == 0);
endmodule

tb/Memory/DepFIFO_tb.sv
// -----------------------------------------------------------------------------
// DepFIFO_tb.sv
//   Directed self-checking testbench for DepFIFO.
//   Run: do scripts/sim/runlab.do DepFIFO
//
//   Tests:
//     1.  Reset clears mem, asserts empty, deasserts full.
//     2.  Push-only to full.
//     3.  Pop-only to empty.
//     4.  Simultaneous push+pop — mem unchanged.
//     5.  Overflow guard: push when full (SPEC test — FAILS until RTL clamping added).
//     6.  Underflow guard: pop when empty (SPEC test — FAILS until RTL clamping added).
//     7.  full/empty flag timing at boundary values.
//     8.  Back-to-back push/pop sequence (no over/underflow in stimulus).
//     9.  Reset mid-operation.
//
//   SVA:
//     ap_mem_in_range   — mem ∈ [0, DEPTH] (fires on overflow or underflow-wrap)
//     ap_full_correct   — full ↔ mem==DEPTH
//     ap_empty_correct  — empty ↔ mem==0
//     ap_mutex          — !(full && empty)
//     ap_no_x_full/empty — no X/Z on outputs
// -----------------------------------------------------------------------------
`timescale 1ns/1ps
`default_nettype none

module DepFIFO_tb;

    // ---- Parameters ----------------------------------------------------------
    localparam int DEPTH      = 4;
    localparam int MEM_W      = $clog2(DEPTH) + 1;   // 3 bits: can hold 0..7
    localparam int CLK_HALF   = 5;                    // 100 MHz
    localparam int RESET_CYC  = 4;
    localparam int TIMEOUT_NS = 10_000;

    // ---- DUT signals ---------------------------------------------------------
    logic clk, rst;
    logic push, pop;
    logic full, empty;

    // ---- DUT -----------------------------------------------------------------
    DepFIFO #(.DEPTH(DEPTH)) dut (
        .clk   (clk),
        .rst   (rst),
        .push  (push),
        .pop   (pop),
        .full  (full),
        .empty (empty)
    );

    // ---- Clock ---------------------------------------------------------------
    initial clk = 1'b0;
    always #CLK_HALF clk = ~clk;

    // ---- Test bookkeeping ----------------------------------------------------
    int unsigned pass_count = 0;
    int unsigned fail_count = 0;

    task automatic chk(input logic cond, input string msg);
        if (cond) pass_count++;
        else begin
            fail_count++;
            $error("[%0t] FAIL: %s", $time, msg);
        end
    endtask

    // ---- Reference model (clamped — represents spec) -------------------------
    int ref_count = 0;

    function automatic void ref_push_fn();
        if (ref_count < DEPTH) ref_count++;
    endfunction

    function automatic void ref_pop_fn();
        if (ref_count > 0) ref_count--;
    endfunction

    // ---- Saved state ---------------------------------------------------------
    logic [MEM_W-1:0] saved_mem;

    // ---- Reset ---------------------------------------------------------------
    // Active-high synchronous rst. Leaves sim at negedge after deassert.
    task automatic do_reset();
        rst = 1'b1; push = 1'b0; pop = 1'b0;
        repeat (RESET_CYC) @(posedge clk);
        @(negedge clk);
        rst = 1'b0;
        @(negedge clk);
    endtask

    // ---- Single-cycle primitives ---------------------------------------------
    // Each task: drive on negedge → latch on posedge → settle on next negedge.
    // Returns at negedge with outputs stable.

    task automatic do_push();
        @(negedge clk); push = 1'b1; pop = 1'b0;
        @(posedge clk);
        @(negedge clk); push = 1'b0;
    endtask

    task automatic do_pop();
        @(negedge clk); push = 1'b0; pop = 1'b1;
        @(posedge clk);
        @(negedge clk); pop = 1'b0;
    endtask

    task automatic do_push_pop();
        @(negedge clk); push = 1'b1; pop = 1'b1;
        @(posedge clk);
        @(negedge clk); push = 1'b0; pop = 1'b0;
    endtask

    // ---- Back-to-back sequence task ------------------------------------------
    // ops[i][1]=push, ops[i][0]=pop. Stimulus avoids over/underflow.
    task automatic run_op_sequence(input logic [1:0] ops [8]);
        for (int i = 0; i < 8; i++) begin
            @(negedge clk);
            push = ops[i][1]; pop = ops[i][0];
            @(posedge clk);
            @(negedge clk);
            push = 1'b0; pop = 1'b0;
            case (ops[i])
                2'b10: ref_push_fn();
                2'b01: ref_pop_fn();
                default: ;
            endcase
            chk(int'(dut.mem) == ref_count,
                $sformatf("T8 op[%0d]: mem=%0d exp=%0d push=%b pop=%b",
                          i, dut.mem, ref_count, ops[i][1], ops[i][0]));
        end
    endtask

    // ---- Main ----------------------------------------------------------------
    initial begin
        $dumpfile("DepFIFO_tb.vcd");
        $dumpvars(0, DepFIFO_tb);

        fork begin
            #TIMEOUT_NS;
            $error("TIMEOUT after %0d ns", TIMEOUT_NS);
            $finish;
        end join_none

        // =====================================================================
        // TEST 1: Reset
        // =====================================================================
        $display("-- TEST 1: Reset");
        do_reset();
        chk(empty   === 1'b1, "T1: empty asserted after reset");
        chk(full    === 1'b0, "T1: full deasserted after reset");
        chk(dut.mem === '0,   "T1: mem == 0 after reset");

        // =====================================================================
        // TEST 2: Push-only to full
        // =====================================================================
        $display("-- TEST 2: Push to full");
        do_reset();
        repeat (DEPTH) do_push();
        chk(full          === 1'b1, "T2: full after DEPTH pushes");
        chk(empty         === 1'b0, "T2: empty deasserted");
        chk(int'(dut.mem) == DEPTH, "T2: mem == DEPTH");

        // =====================================================================
        // TEST 3: Pop-only to empty (from full)
        // =====================================================================
        $display("-- TEST 3: Pop to empty");
        repeat (DEPTH) do_pop();
        chk(empty         === 1'b1, "T3: empty after DEPTH pops");
        chk(full          === 1'b0, "T3: full deasserted");
        chk(dut.mem       === '0,   "T3: mem == 0");

        // =====================================================================
        // TEST 4: Simultaneous push+pop — mem must not change
        // =====================================================================
        $display("-- TEST 4: Simultaneous push+pop");
        do_reset();
        do_push(); do_push();          // mem = 2
        saved_mem = dut.mem;
        do_push_pop();
        chk(dut.mem === saved_mem, "T4: mem stable on push+pop");
        chk(full    === 1'b0,      "T4: not full");
        chk(empty   === 1'b0,      "T4: not empty");

        // =====================================================================
        // TEST 5: Overflow guard — push when full
        //   Expected: mem stays == DEPTH. WILL FAIL until RTL clamping added.
        // =====================================================================
        $display("-- TEST 5: Overflow guard");
        do_reset();
        repeat (DEPTH) do_push();
        chk(full === 1'b1, "T5: full before overflow attempt");
        do_push();                     // push on full
        chk(int'(dut.mem) == DEPTH,   "T5: mem unchanged (== DEPTH) on push-when-full");
        chk(full           === 1'b1,  "T5: full remains asserted");

        // =====================================================================
        // TEST 6: Underflow guard — pop when empty
        //   Expected: mem stays == 0. WILL FAIL until RTL clamping added.
        // =====================================================================
        $display("-- TEST 6: Underflow guard");
        do_reset();
        chk(empty === 1'b1, "T6: empty before underflow attempt");
        do_pop();                      // pop on empty
        chk(dut.mem === '0,           "T6: mem stays 0 on pop-when-empty");
        chk(empty   === 1'b1,         "T6: empty remains asserted");

        // =====================================================================
        // TEST 7: full/empty flag timing at boundaries
        // =====================================================================
        $display("-- TEST 7: Flag timing");
        do_reset();
        repeat (DEPTH - 1) do_push();
        chk(full  === 1'b0, "T7: not full at DEPTH-1");
        chk(empty === 1'b0, "T7: not empty at DEPTH-1");
        do_push();                     // -> full
        chk(full  === 1'b1, "T7: full exactly at DEPTH");
        do_pop();                      // -> DEPTH-1
        chk(full  === 1'b0, "T7: full deasserts one below DEPTH");
        repeat (DEPTH - 1) do_pop();   // drain
        chk(empty === 1'b1, "T7: empty after full drain");

        // =====================================================================
        // TEST 8: Back-to-back push/pop (counts stay in [0,2] — no over/underflow)
        //   Sequence: push push pop push pop pop push push
        //   Expected: 1    2    1   2    1   0   1    2
        // =====================================================================
        $display("-- TEST 8: Back-to-back");
        do_reset(); ref_count = 0;
        begin
            automatic logic [1:0] ops [8] = '{2'b10, 2'b10, 2'b01, 2'b10,
                                              2'b01, 2'b01, 2'b10, 2'b10};
            run_op_sequence(ops);
        end

        // =====================================================================
        // TEST 9: Reset mid-operation
        // =====================================================================
        $display("-- TEST 9: Reset mid-operation");
        do_reset();
        do_push(); do_push();
        chk(int'(dut.mem) == 2, "T9: mem==2 before mid-reset");
        do_reset();
        chk(empty   === 1'b1, "T9: empty after mid-reset");
        chk(dut.mem === '0,   "T9: mem==0 after mid-reset");

        // ---- Report ----------------------------------------------------------
        $display("------------------------------------------------------------");
        $display("Tests run : %0d", pass_count + fail_count);
        $display("Passed    : %0d", pass_count);
        $display("Failed    : %0d", fail_count);
        if (fail_count == 0)
            $display("PASS");
        else
            $display("FAIL");
        $display("------------------------------------------------------------");
        $finish;
    end

    // =========================================================================
    // SVA: concurrent assertions [IEEE 1800-2017 §16]
    // =========================================================================

    // mem in [0..DEPTH] — catches overflow and underflow-wrap simultaneously
    property p_mem_in_range;
        @(posedge clk) disable iff (rst)
        dut.mem <= MEM_W'(DEPTH);
    endproperty
    ap_mem_in_range: assert property (p_mem_in_range)
        else $error("[%0t] SVA: mem=%0d out of [0..%0d]", $time, dut.mem, DEPTH);

    // full ↔ mem == DEPTH (combinational equivalence)
    property p_full_correct;
        @(posedge clk) disable iff (rst)
        full == (dut.mem == MEM_W'(DEPTH));
    endproperty
    ap_full_correct: assert property (p_full_correct)
        else $error("[%0t] SVA: full=%b mem=%0d", $time, full, dut.mem);

    // empty ↔ mem == 0
    property p_empty_correct;
        @(posedge clk) disable iff (rst)
        empty == (dut.mem == '0);
    endproperty
    ap_empty_correct: assert property (p_empty_correct)
        else $error("[%0t] SVA: empty=%b mem=%0d", $time, empty, dut.mem);

    // full and empty mutually exclusive
    property p_mutex;
        @(posedge clk) disable iff (rst)
        !(full && empty);
    endproperty
    ap_mutex: assert property (p_mutex)
        else $error("[%0t] SVA: full && empty both high", $time);

    // No X/Z on outputs after reset
    property p_no_x_full;
        @(posedge clk) disable iff (rst) !$isunknown(full);
    endproperty
    ap_no_x_full: assert property (p_no_x_full)
        else $error("[%0t] SVA: full is X/Z", $time);

    property p_no_x_empty;
        @(posedge clk) disable iff (rst) !$isunknown(empty);
    endproperty
    ap_no_x_empty: assert property (p_no_x_empty)
        else $error("[%0t] SVA: empty is X/Z", $time);

    // Cover properties
    cp_full_hit:  cover property (@(posedge clk) $rose(full));
    cp_empty_hit: cover property (@(posedge clk) $rose(empty));

endmodule

`default_nettype wire

tb/vcd/DepFIFO_tb.vcd
$date
	Tue May 26 19:06:44 2026
$end
$version
	ModelSim Version 10.5b
$end
$timescale
	1ps
$end

$scope module DepFIFO_tb $end
$var parameter 32 ! DEPTH $end
$var parameter 32 " MEM_W $end
$var parameter 32 # CLK_HALF $end
$var parameter 32 $ RESET_CYC $end
$var parameter 32 % TIMEOUT_NS $end
$var reg 1 & clk $end
$var reg 1 ' rst $end
$var reg 1 ( push $end
$var reg 1 ) pop $end
$var reg 1 * full $end
$var reg 1 + empty $end
$var integer 32 , pass_count $end
$var integer 32 - fail_count $end
$var integer 32 . ref_count $end
$var reg 3 / saved_mem [2:0] $end

$scope task chk $end
$upscope $end

$scope function ref_push_fn $end
$upscope $end

$scope function ref_pop_fn $end
$upscope $end

$scope task do_reset $end
$upscope $end

$scope task do_push $end
$upscope $end

$scope task do_pop $end
$upscope $end

$scope task do_push_pop $end
$upscope $end

$scope task run_op_sequence $end
$upscope $end

$scope begin ap_mem_in_range $end
$upscope $end

$scope begin ap_full_correct $end
$upscope $end

$scope begin ap_empty_correct $end
$upscope $end

$scope begin ap_mutex $end
$upscope $end

$scope begin ap_no_x_full $end
$upscope $end

$scope begin ap_no_x_empty $end
$upscope $end

$scope begin cp_full_hit $end
$upscope $end

$scope begin cp_empty_hit $end
$upscope $end

$scope module dut $end
$var parameter 32 0 DEPTH $end
$var wire 1 1 clk $end
$var wire 1 2 rst $end
$var wire 1 3 push $end
$var wire 1 4 pop $end
$var reg 1 5 full $end
$var reg 1 6 empty $end
$var reg 3 7 mem [2:0] $end
$upscope $end
$upscope $end
$enddefinitions $end
#0
$dumpvars
0&
1'
0(
0)
x*
x+
x5
x6
bx 7
bx /
b100 !
b11 "
b101 #
b100 $
b10011100010000 %
b100 0
b0 ,
b0 -
b0 .
01
12
03
04
$end
#5000
1&
11
b0 7
05
16
1+
0*
#10000
0&
01
#15000
1&
11
#20000
0&
01
#25000
1&
11
#30000
0&
01
#35000
1&
11
#40000
0&
01
0'
02
#45000
1&
11
#50000
0&
01
b1 ,
b10 ,
b11 ,
1'
12
#55000
1&
11
#60000
0&
01
#65000
1&
11
#70000
0&
01
#75000
1&
11
#80000
0&
01
#85000
1&
11
#90000
0&
01
0'
02
#95000
1&
11
#100000
0&
01
#105000
1&
11
#110000
0&
01
1(
13
#115000
1&
11
b1 7
06
0+
#120000
0&
01
0(
03
#125000
1&
11
#130000
0&
01
1(
13
#135000
1&
11
b10 7
#140000
0&
01
0(
03
#145000
1&
11
#150000
0&
01
1(
13
#155000
1&
11
b11 7
#160000
0&
01
0(
03
#165000
1&
11
#170000
0&
01
1(
13
#175000
1&
11
b100 7
15
1*
#180000
0&
01
0(
b100 ,
b101 ,
b110 ,
03
#185000
1&
11
#190000
0&
01
1)
14
#195000
1&
11
b11 7
05
0*
#200000
0&
01
0)
04
#205000
1&
11
#210000
0&
01
1)
14
#215000
1&
11
b10 7
#220000
0&
01
0)
04
#225000
1&
11
#230000
0&
01
1)
14
#235000
1&
11
b1 7
#240000
0&
01
0)
04
#245000
1&
11
#250000
0&
01
1)
14
#255000
1&
11
b0 7
16
1+
#260000
0&
01
0)
b111 ,
b1000 ,
b1001 ,
1'
04
12
#265000
1&
11
#270000
0&
01
#275000
1&
11
#280000
0&
01
#285000
1&
11
#290000
0&
01
#295000
1&
11
#300000
0&
01
0'
02
#305000
1&
11
#310000
0&
01
#315000
1&
11
#320000
0&
01
1(
13
#325000
1&
11
b1 7
06
0+
#330000
0&
01
0(
03
#335000
1&
11
#340000
0&
01
1(
13
#345000
1&
11
b10 7
#350000
0&
01
0(
b10 /
03
#355000
1&
11
#360000
0&
01
1(
1)
13
14
#365000
1&
11
#370000
0&
01
0(
0)
b1010 ,
b1011 ,
b1100 ,
1'
03
04
12
#375000
1&
11
b0 7
16
1+
#380000
0&
01
#385000
1&
11
#390000
0&
01
#395000
1&
11
#400000
0&
01
#405000
1&
11
#410000
0&
01
0'
02
#415000
1&
11
#420000
0&
01
#425000
1&
11
#430000
0&
01
1(
13
#435000
1&
11
b1 7
06
0+
#440000
0&
01
0(
03
#445000
1&
11
#450000
0&
01
1(
13
#455000
1&
11
b10 7
#460000
0&
01
0(
03
#465000
1&
11
#470000
0&
01
1(
13
#475000
1&
11
b11 7
#480000
0&
01
0(
03
#485000
1&
11
#490000
0&
01
1(
13
#495000
1&
11
b100 7
15
1*
#500000
0&
01
0(
b1101 ,
03
#505000
1&
11
#510000
0&
01
1(
13
#515000
1&
11
#520000
0&
01
0(
b1110 ,
b1111 ,
1'
03
12
#525000
1&
11
b0 7
05
16
1+
0*
#530000
0&
01
#535000
1&
11
#540000
0&
01
#545000
1&
11
#550000
0&
01
#555000
1&
11
#560000
0&
01
0'
02
#565000
1&
11
#570000
0&
01
b10000 ,
#575000
1&
11
#580000
0&
01
1)
14
#585000
1&
11
#590000
0&
01
0)
b10001 ,
b10010 ,
1'
04
12
#595000
1&
11
#600000
0&
01
#605000
1&
11
#610000
0&
01
#615000
1&
11
#620000
0&
01
#625000
1&
11
#630000
0&
01
0'
02
#635000
1&
11
#640000
0&
01
#645000
1&
11
#650000
0&
01
1(
13
#655000
1&
11
b1 7
06
0+
#660000
0&
01
0(
03
#665000
1&
11
#670000
0&
01
1(
13
#675000
1&
11
b10 7
#680000
0&
01
0(
03
#685000
1&
11
#690000
0&
01
1(
13
#695000
1&
11
b11 7
#700000
0&
01
0(
b10011 ,
b10100 ,
03
#705000
1&
11
#710000
0&
01
1(
13
#715000
1&
11
b100 7
15
1*
#720000
0&
01
0(
b10101 ,
03
#725000
1&
11
#730000
0&
01
1)
14
#735000
1&
11
b11 7
05
0*
#740000
0&
01
0)
b10110 ,
04
#745000
1&
11
#750000
0&
01
1)
14
#755000
1&
11
b10 7
#760000
0&
01
0)
04
#765000
1&
11
#770000
0&
01
1)
14
#775000
1&
11
b1 7
#780000
0&
01
0)
04
#785000
1&
11
#790000
0&
01
1)
14
#795000
1&
11
b0 7
16
1+
#800000
0&
01
0)
b10111 ,
1'
04
12
#805000
1&
11
#810000
0&
01
#815000
1&
11
#820000
0&
01
#825000
1&
11
#830000
0&
01
#835000
1&
11
#840000
0&
01
0'
02
#845000
1&
11
#850000
0&
01
#855000
1&
11
#860000
0&
01
1(
13
#865000
1&
11
b1 7
06
0+
#870000
0&
01
0(
b1 .
b11000 ,
03
#875000
1&
11
#880000
0&
01
1(
13
#885000
1&
11
b10 7
#890000
0&
01
0(
b10 .
b11001 ,
03
#895000
1&
11
#900000
0&
01
1)
14
#905000
1&
11
b1 7
#910000
0&
01
0)
b1 .
b11010 ,
04
#915000
1&
11
#920000
0&
01
1(
13
#925000
1&
11
b10 7
#930000
0&
01
0(
b10 .
b11011 ,
03
#935000
1&
11
#940000
0&
01
1)
14
#945000
1&
11
b1 7
#950000
0&
01
0)
b1 .
b11100 ,
04
#955000
1&
11
#960000
0&
01
1)
14
#965000
1&
11
b0 7
16
1+
#970000
0&
01
0)
b0 .
b11101 ,
04
#975000
1&
11
#980000
0&
01
1(
13
#985000
1&
11
b1 7
06
0+
#990000
0&
01
0(
b1 .
b11110 ,
03
#995000
1&
11
#1000000
0&
01
1(
13
#1005000
1&
11
b10 7
#1010000
0&
01
0(
b10 .
b11111 ,
1'
03
12
#1015000
1&
11
b0 7
16
1+
#1020000
0&
01
#1025000
1&
11
#1030000
0&
01
#1035000
1&
11
#1040000
0&
01
#1045000
1&
11
#1050000
0&
01
0'
02
#1055000
1&
11
#1060000
0&
01
#1065000
1&
11
#1070000
0&
01
1(
13
#1075000
1&
11
b1 7
06
0+
#1080000
0&
01
0(
03
#1085000
1&
11
#1090000
0&
01
1(
13
#1095000
1&
11
b10 7
#1100000
0&
01
0(
b100000 ,
1'
03
12
#1105000
1&
11
b0 7
16
1+
#1110000
0&
01
#1115000
1&
11
#1120000
0&
01
#1125000
1&
11
#1130000
0&
01
#1135000
1&
11
#1140000
0&
01
0'
02
#1145000
1&
11
#1150000
0&
01
b100001 ,
b100010 ,
